dometl/__init__.py
dometl/config.py
dometl/db_utils.py
dometl/etl_runner.py
dometl/settings.py
dometl-0.0.1.dist-info/LICENSE
dometl-0.0.1.dist-info/METADATA
dometl-0.0.1.dist-info/WHEEL
dometl-0.0.1.dist-info/entry_points.txt
dometl-0.0.1.dist-info/top_level.txt
dometl-0.0.1.dist-info/RECORD
