Metadata-Version: 2.1
Name: dometl
Version: 0.0.1
Summary: Simple python ETL tool.
Author-email: Dominik Zulovec Sajovic <dominik.zsajovic@gmail.com>
License: MIT License
Project-URL: Homepage, https://github.com/orion512/dometl
Keywords: etl,csv,postgres,python
Classifier: Programming Language :: Python :: 3
Classifier: License :: OSI Approved :: MIT License
Classifier: Operating System :: OS Independent
Requires-Python: >=3.9
License-File: LICENSE
Requires-Dist: psycopg2 (==2.9.5)
Requires-Dist: PyYAML (==6.0)
